padsniff/__init__.py
padsniff/certs.py
padsniff/cli.py
padsniff/constants.py
padsniff/parallel.py
padsniff/proxy.py
padsniff/structures.py
padsniff-1.2.1.dist-info/DESCRIPTION.rst
padsniff-1.2.1.dist-info/METADATA
padsniff-1.2.1.dist-info/RECORD
padsniff-1.2.1.dist-info/WHEEL
padsniff-1.2.1.dist-info/entry_points.txt
padsniff-1.2.1.dist-info/metadata.json
padsniff-1.2.1.dist-info/top_level.txt
