Metadata-Version: 2.0
Name: padsniff
Version: 1.2.1
Summary: Command-line tool to sniff Puzzle & Dragons data.
Home-page: https://gitlab.com/wmedlar/padsniff
Author: Will Medlar
Author-email: will.medlar@gmail.com
License: MIT
Keywords: puzzle & dragons,man-in-the-middle,reverse engineering
Platform: UNKNOWN
Classifier: Development Status :: 5 - Production/Stable
Classifier: Environment :: Console
Classifier: Intended Audience :: Developers
Classifier: Programming Language :: Python :: 3
Classifier: Programming Language :: Python :: 3.5
Classifier: Programming Language :: Python :: 3.6
Classifier: Programming Language :: Python :: 3 :: Only
Classifier: Topic :: Games/Entertainment :: Puzzle Games
Requires-Dist: click (==6.7)
Requires-Dist: mitmproxy (==2.0.2)
Requires-Dist: pyOpenSSL (==16.2.0)
